pytest_circleci/__init__.py
pytest_circleci/plugin.py
pytest_circleci-0.0.3.dist-info/LICENSE
pytest_circleci-0.0.3.dist-info/METADATA
pytest_circleci-0.0.3.dist-info/WHEEL
pytest_circleci-0.0.3.dist-info/entry_points.txt
pytest_circleci-0.0.3.dist-info/top_level.txt
pytest_circleci-0.0.3.dist-info/RECORD
