Metadata-Version: 2.1
Name: pytest-circleci
Version: 0.0.3
Summary: py.test plugin for CircleCI
Home-page: https://github.com/micktwomey/pytest-circleci
Author: Michael Twomey
Author-email: mick@twomeylee.name
License: UNKNOWN
Platform: UNKNOWN
Classifier: License :: OSI Approved :: MIT License
Classifier: Programming Language :: Python :: 2
Classifier: Programming Language :: Python :: 3
